multibase/__init__.py
multibase/converters.py
multibase/multibase.py
py_multibase-1.0.3.dist-info/AUTHORS.rst
py_multibase-1.0.3.dist-info/LICENSE
py_multibase-1.0.3.dist-info/METADATA
py_multibase-1.0.3.dist-info/WHEEL
py_multibase-1.0.3.dist-info/top_level.txt
py_multibase-1.0.3.dist-info/RECORD
