Metadata-Version: 1.1
Name: py-multibase
Version: 1.0.3
Summary: Multibase implementation for Python
Home-page: https://github.com/multiformats/py-multibase
Author: Dhruv Baldawa
Author-email: dhruv@dhruvb.com
License: MIT license
Keywords: multibase
Platform: UNKNOWN
Classifier: Development Status :: 2 - Pre-Alpha
Classifier: Intended Audience :: Developers
Classifier: License :: OSI Approved :: MIT License
Classifier: Natural Language :: English
Classifier: Programming Language :: Python :: 3.4
Classifier: Programming Language :: Python :: 3.5
